[
  {
    "id": "b0a2ca1e-5664-4b53-a5b2-199e9afa24de",
    "data": [
      {
        "text": "options",
        "userDefined": false
      }
    ],
    "isTemplate": false,
    "count": 0,
    "lang": "en",
    "updated": 0
  },
  {
    "id": "5a885e43-2783-480b-983e-b131234395fa",
    "data": [
      {
        "text": "I need help",
        "userDefined": false
      }
    ],
    "isTemplate": false,
    "count": 0,
    "lang": "en",
    "updated": 0
  },
  {
    "id": "74d038c1-2df4-4b08-b37d-25fa06824cb2",
    "data": [
      {
        "text": "get help",
        "userDefined": false
      }
    ],
    "isTemplate": false,
    "count": 0,
    "lang": "en",
    "updated": 0
  },
  {
    "id": "62efa1da-f6e5-4bc8-a54e-6943386f7e5c",
    "data": [
      {
        "text": "help",
        "userDefined": false
      }
    ],
    "isTemplate": false,
    "count": 0,
    "lang": "en",
    "updated": 0
  }
]